tests/__init__.py
tests/test_models.py
tests/test_tsetmc.py
tse_utils/__init__.py
tse_utils/models/__init__.py
tse_utils/models/enums.py
tse_utils/models/instrument.py
tse_utils/models/realtime.py
tse_utils/models/trader.py
tse_utils/tse_client/__init__.py
tse_utils/tse_client/app.py
tse_utils/tse_client/models.py
tse_utils/tsetmc/__init__.py
tse_utils/tsetmc/app.py
tse_utils/tsetmc/models.py
tse_utils-1.1.5.dist-info/METADATA
tse_utils-1.1.5.dist-info/WHEEL
tse_utils-1.1.5.dist-info/top_level.txt
tse_utils-1.1.5.dist-info/RECORD
