Metadata-Version: 2.1
Name: tse_utils
Version: 1.1.5
Summary: General utilities used for data mining in Tehran Stock Exchange (TSE).
Author: Arka Equities & Securities
Author-email: info@arkaequities.com
Classifier: Programming Language :: Python :: 3
Classifier: Operating System :: POSIX :: Linux
Classifier: Operating System :: MacOS :: MacOS X
Classifier: Operating System :: Microsoft :: Windows
Requires-Dist: httpx
Requires-Dist: beautifulsoup4
Requires-Dist: lxml
